LICENSE
MANIFEST.in
README.rst
setup.py
django_comments_easy.egg-info/PKG-INFO
django_comments_easy.egg-info/SOURCES.txt
django_comments_easy.egg-info/dependency_links.txt
django_comments_easy.egg-info/top_level.txt
django_commentseasy/__init__.py
django_commentseasy/admin.py
django_commentseasy/apps.py
django_commentseasy/forms.py
django_commentseasy/models.py
django_commentseasy/tests.py
django_commentseasy/urls.py
django_commentseasy/views.py
django_commentseasy/templates/django_commentseasy/base.html
django_commentseasy/templates/django_commentseasy/bootstrap_files.html
django_commentseasy/templates/django_commentseasy/comment_box.html
django_commentseasy/templates/django_commentseasy/comment_form.html
django_commentseasy/templates/django_commentseasy/comment_viewer.html
django_commentseasy/templates/django_commentseasy/like_button.html
django_commentseasy/templates/django_commentseasy/remove_button.html
django_commentseasy/templates/django_commentseasy/render_comment_data.html
django_commentseasy/templates/django_commentseasy/reply_form.html
django_commentseasy/templates/django_commentseasy/reply_viewer.html
django_commentseasy/templatetags/__init__.py
django_commentseasy/templatetags/django_comments_easy.py